HISTORY.rst
MANIFEST.in
README.rst
setup.py
tracery/__init__.py
tracery/__main__.py
tracery/modifiers.py
tracery.egg-info/PKG-INFO
tracery.egg-info/SOURCES.txt
tracery.egg-info/dependency_links.txt
tracery.egg-info/top_level.txt
tracery.egg-info/zip-safe